dbispipeline/__init__.py
dbispipeline/__main__.py
dbispipeline/analytics.py
dbispipeline/base.py
dbispipeline/cli/__init__.py
dbispipeline/cli/dataset.py
dbispipeline/cli/main.py
dbispipeline/core.py
dbispipeline/dataloaders/__init__.py
dbispipeline/dataloaders/csv.py
dbispipeline/dataloaders/dataframe.py
dbispipeline/dataloaders/explicit.py
dbispipeline/dataloaders/json_playlist_loader.py
dbispipeline/dataloaders/testing_utils.py
dbispipeline/dataloaders/wrappers.py
dbispipeline/db.py
dbispipeline/evaluators.py
dbispipeline/models.py
dbispipeline/pipeline/__init__.py
dbispipeline/pipeline/basic.py
dbispipeline/pipeline/filename.py
dbispipeline/pipeline/strings.py
dbispipeline/result_handlers.py
dbispipeline/storage_handlers.py
dbispipeline/utils.py
dbispipeline-0.9.dist-info/LICENSE
dbispipeline-0.9.dist-info/METADATA
dbispipeline-0.9.dist-info/WHEEL
dbispipeline-0.9.dist-info/entry_points.txt
dbispipeline-0.9.dist-info/RECORD
