Metadata-Version: 2.1
Name: dbispipeline
Version: 0.9
Summary: For logging scientific experiments
Author: Benjamin Murauer
Author-email: b.murauer@posteo.de
Requires-Python: >=3.9
Classifier: Programming Language :: Python :: 3
Classifier: Programming Language :: Python :: 3.9
Classifier: Programming Language :: Python :: 3.10
Classifier: Programming Language :: Python :: 3.11
Requires-Dist: click (>=8.1.7,<9.0.0)
Requires-Dist: gitpython (>=3.1.36,<4.0.0)
Requires-Dist: logzero (>=1.7.0,<2.0.0)
Requires-Dist: matplotlib (>=3.7.3,<4.0.0)
Requires-Dist: pandas (>=2.1.0,<3.0.0)
Requires-Dist: pyyaml (>=6.0.1,<7.0.0)
Requires-Dist: scikit-learn (>=1.3.0,<2.0.0)
Requires-Dist: sqlalchemy (>=2.0.20,<3.0.0)
